aipype_extras/__init__.py
aipype_extras/py.typed
aipype_extras/llm_log_viewer/README.md
aipype_extras/llm_log_viewer/__init__.py
aipype_extras/llm_log_viewer/__main__.py
aipype_extras/llm_log_viewer/llm_log_viewer.py
aipype_extras/llm_log_viewer/run_viewer.sh
aipype_extras/llm_log_viewer/static/script.js
aipype_extras/llm_log_viewer/static/style.css
aipype_extras/llm_log_viewer/templates/index.html
aipype_extras-0.1.0a5.dist-info/METADATA
aipype_extras-0.1.0a5.dist-info/WHEEL
aipype_extras-0.1.0a5.dist-info/entry_points.txt
aipype_extras-0.1.0a5.dist-info/RECORD
